cli/__init__.py
cli/ac_class_contents.py
cli/ac_func_contents.py
cli/class_contents.py
cli/cli.py
cli/func_contents.py
flet_route/__init__.py
flet_route/basket.py
flet_route/not_found_view.py
flet_route/params.py
flet_route/routing.py
flet_route-0.3.3.dist-info/LICENSE
flet_route-0.3.3.dist-info/METADATA
flet_route-0.3.3.dist-info/WHEEL
flet_route-0.3.3.dist-info/entry_points.txt
flet_route-0.3.3.dist-info/top_level.txt
flet_route-0.3.3.dist-info/RECORD
